ire/__init__.py
ire/dvc.py
ire/git.py
ire/ire.py
ire/md.py
ire/utils.py
iRe.py-0.4.1.dist-info/LICENSE
iRe.py-0.4.1.dist-info/METADATA
iRe.py-0.4.1.dist-info/WHEEL
iRe.py-0.4.1.dist-info/top_level.txt
iRe.py-0.4.1.dist-info/RECORD
