Metadata-Version: 2.1
Name: iRe.py
Version: 0.4.1
Summary: Export tables and plots from Jupyter notebooks, along with metadata for embedding interactive tables in downstream apps.
Home-page: https://gitlab.com/runsascoded/ire/py
Author: Ryan Williams
Author-email: ryan@runsascoded.com
License: MIT
License-File: LICENSE
Requires-Dist: click
Requires-Dist: ipython
Requires-Dist: pandas
Requires-Dist: SQLAlchemy
Requires-Dist: utz >=0.4.2
Provides-Extra: plotly
Requires-Dist: plotly ; extra == 'plotly'
Provides-Extra: test
Requires-Dist: dvc ; extra == 'test'
Requires-Dist: dvc-s3 ; extra == 'test'
Requires-Dist: jupyter ; extra == 'test'
Requires-Dist: juq.py ; extra == 'test'
Requires-Dist: nbval ; extra == 'test'
Requires-Dist: papermill ; extra == 'test'
Requires-Dist: plotly ; extra == 'test'
Requires-Dist: pytest <8.1 ; extra == 'test'
Requires-Dist: pytest-cov ; extra == 'test'
Requires-Dist: fastparquet ==2024.2.0 ; extra == 'test'
Requires-Dist: matplotlib ==3.8.2 ; extra == 'test'
Requires-Dist: pandas ==2.1.4 ; extra == 'test'
Requires-Dist: html5lib ; extra == 'test'
Requires-Dist: kaleido ; extra == 'test'
Requires-Dist: lxml ; extra == 'test'
